qdr.py
quickdebrepo-0.0.2.dist-info/DESCRIPTION.rst
quickdebrepo-0.0.2.dist-info/METADATA
quickdebrepo-0.0.2.dist-info/RECORD
quickdebrepo-0.0.2.dist-info/WHEEL
quickdebrepo-0.0.2.dist-info/entry_points.txt
quickdebrepo-0.0.2.dist-info/metadata.json
quickdebrepo-0.0.2.dist-info/top_level.txt
