Metadata-Version: 2.0
Name: quickdebrepo
Version: 0.0.2
Summary: Quickly host your own debian/apt repo
Home-page: UNKNOWN
Author: Joe Gillotti
Author-email: joe@u13.net
License: MIT
Platform: UNKNOWN
